odoo10_addon_shopinvader_payment_paypal-10.0.1.0.0.99.dev5-nspkg.pth
odoo/addons/shopinvader_payment_paypal/README.rst
odoo/addons/shopinvader_payment_paypal/__init__.py
odoo/addons/shopinvader_payment_paypal/__manifest__.py
odoo/addons/shopinvader_payment_paypal/demo/shopinvader_payment_demo.xml
odoo/addons/shopinvader_payment_paypal/models/__init__.py
odoo/addons/shopinvader_payment_paypal/models/shopinvader_payment.py
odoo/addons/shopinvader_payment_paypal/services/__init__.py
odoo/addons/shopinvader_payment_paypal/services/payment_service.py
odoo/addons/shopinvader_payment_paypal/static/description/icon.png
odoo/addons/shopinvader_payment_paypal/tests/__init__.py
odoo/addons/shopinvader_payment_paypal/tests/test_payment.py
odoo/addons/shopinvader_payment_paypal/views/shopinvader_payment.xml
odoo10_addon_shopinvader_payment_paypal-10.0.1.0.0.99.dev5.dist-info/METADATA
odoo10_addon_shopinvader_payment_paypal-10.0.1.0.0.99.dev5.dist-info/WHEEL
odoo10_addon_shopinvader_payment_paypal-10.0.1.0.0.99.dev5.dist-info/namespace_packages.txt
odoo10_addon_shopinvader_payment_paypal-10.0.1.0.0.99.dev5.dist-info/top_level.txt
odoo10_addon_shopinvader_payment_paypal-10.0.1.0.0.99.dev5.dist-info/RECORD
