Metadata-Version: 2.1
Name: odoo10-addon-shopinvader-payment-paypal
Version: 10.0.1.0.0.99.dev5
Summary: Shopinvader Paypal Payment Gateway
Home-page: https://akretion.com
Author: Akretion
License: AGPL-3
Platform: UNKNOWN
Classifier: Programming Language :: Python
Classifier: Framework :: Odoo
Classifier: License :: OSI Approved :: GNU Affero General Public License v3
Requires-Python: ~=2.7
Requires-Dist: odoo10-addon-payment-gateway-paypal
Requires-Dist: odoo10-addon-shopinvader-payment
Requires-Dist: odoo (<10.1dev,>=10.0)
Requires-Dist: paypalrestsdk
